setup.py
st_distributions/Binomialdistribution.py
st_distributions/Gaussiandistribution.py
st_distributions/Generaldistribution.py
st_distributions/__init__.py
st_distributions.egg-info/PKG-INFO
st_distributions.egg-info/SOURCES.txt
st_distributions.egg-info/dependency_links.txt
st_distributions.egg-info/not-zip-safe
st_distributions.egg-info/top_level.txt