Metadata-Version: 1.0
Name: st-distributions
Version: 0.1
Summary: Gaussian distributions
Home-page: UNKNOWN
Author: Yifei Tong
Author-email: tongyf.shane2013@outlook.com
License: UNKNOWN
Platform: UNKNOWN
